django_mail_analytics/__init__.py
django_mail_analytics/admin.py
django_mail_analytics/apps.py
django_mail_analytics/mail.py
django_mail_analytics/metadata.py
django_mail_analytics/models.py
django_mail_analytics/tests.py
django_mail_analytics/urls.py
django_mail_analytics/views.py
django_mail_analytics/migrations/0001_initial.py
django_mail_analytics/migrations/__init__.py
django_mail_analytics/templates/django_mail_analytics/mail_list.html
django_mail_analytics-1.0.3.dist-info/LICENSE.txt
django_mail_analytics-1.0.3.dist-info/METADATA
django_mail_analytics-1.0.3.dist-info/WHEEL
django_mail_analytics-1.0.3.dist-info/top_level.txt
django_mail_analytics-1.0.3.dist-info/RECORD
