Metadata-Version: 2.1
Name: django-mail-analytics
Version: 1.0.3
Summary: django package adding email tracking features.  Both email opening and link clicking are tracked.
Author-email: Loic Quertenmont <loic@deeperanalytics.be>
Maintainer-email: Loic Quertenmont <loic@deeperanalytics.be>
License: MIT License
Project-URL: Homepage, https://github.com/quertenmont/django-mail-analytics
Project-URL: Download, https://github.com/quertenmont/django-mail-analytics/releases
Project-URL: Documentation, https://github.com/quertenmont/django-mail-analytics#readme
Project-URL: Issues, https://github.com/quertenmont/django-mail-analytics/issues
Project-URL: Funding, https://github.com/sponsors/quertenmont/
Project-URL: Twitter, https://twitter.com/LoicQuertenmont
Keywords: django,mail,analytics,tracking,tracker,python
Classifier: Development Status :: 5 - Production/Stable
Classifier: Environment :: Web Environment
Classifier: Framework :: Django
Classifier: Framework :: Django :: 5.0
Classifier: Intended Audience :: Developers
Classifier: License :: OSI Approved :: MIT License
Classifier: Natural Language :: English
Classifier: Operating System :: OS Independent
Classifier: Programming Language :: Python :: 3.11
Classifier: Programming Language :: Python :: 3.12
Classifier: Topic :: Software Development :: Build Tools
License-File: LICENSE.txt
